Metadata-Version: 1.0
Name: basic-xl-distributions
Version: 1.0
Summary: Gaussian and Binomial distributions
Home-page: UNKNOWN
Author: Rocio Cruz Linares
Author-email: rocio.x.linares95@gmail.com
License: UNKNOWN
Platform: UNKNOWN
